linepipe/__init__.py
linepipe/node.py
linepipe/pipeline.py
linepipe/registry.py
linepipe/viz.py
linepipe-0.2.2.dist-info/METADATA
linepipe-0.2.2.dist-info/WHEEL
linepipe-0.2.2.dist-info/licenses/LICENSE
linepipe-0.2.2.dist-info/RECORD
