Metadata-Version: 2.4
Name: linepipe
Version: 0.2.2
Summary: Composable, linear pipelines
License: MIT
License-File: LICENSE
Keywords: pipeline,data-processing
Author: Marek Kancir
Author-email: kancir.marek@gmail.com
Requires-Python: >=3.11, !=2.7.*, !=3.0.*, !=3.1.*, !=3.2.*, !=3.3.*, !=3.4.*, !=3.5.*, !=3.6.*, !=3.7.*, !=3.8.*, !=3.9.*, !=3.10.*
Classifier: Development Status :: 3 - Alpha
Classifier: Intended Audience :: Developers
Classifier: License :: OSI Approved :: MIT License
Classifier: Programming Language :: Python :: 3
Classifier: Programming Language :: Python :: 3.11
Classifier: Programming Language :: Python :: 3.12
Classifier: Programming Language :: Python :: 3.13
Classifier: Programming Language :: Python :: 3.14
Provides-Extra: memory
Provides-Extra: plot
Requires-Dist: memory-profiler (==0.61.0) ; extra == "memory"
Requires-Dist: networkx (==3.6.1) ; extra == "plot"
Requires-Dist: plotly (==6.5.2) ; extra == "plot"
Project-URL: Homepage, https://github.com/marek-kan/linepipe
Project-URL: Repository, https://github.com/marek-kan/linepipe
